Tee_Logger.py
tee_logger-6.37.dist-info/METADATA
tee_logger-6.37.dist-info/WHEEL
tee_logger-6.37.dist-info/top_level.txt
tee_logger-6.37.dist-info/RECORD
