Metadata-Version: 2.4
Name: tee-logger
Version: 6.37
Summary: A simple wrapper for python logger that also selectively tee logs to stdout
Author-email: Yufei Pan <pan@zopyr.us>
License: GPL-3.0-or-later
Project-URL: Homepage, https://github.com/yufei-pan/Tee_Logger
Classifier: License :: OSI Approved :: GNU General Public License v3 or later (GPLv3+)
Classifier: Programming Language :: Python :: 3
Classifier: Operating System :: OS Independent
Requires-Python: >=3.6
Requires-Dist: python-dateutil
